berry_check/__init__.py
berry_check/check.py
berrycheck-1.0.5.dist-info/LICENSE
berrycheck-1.0.5.dist-info/METADATA
berrycheck-1.0.5.dist-info/WHEEL
berrycheck-1.0.5.dist-info/top_level.txt
berrycheck-1.0.5.dist-info/RECORD
