Metadata-Version: 2.1
Name: berrycheck
Version: 1.0.5
Summary: Fornecer aos usuários uma maneira fácil e acessível de obter cotações atualizadas de várias moedas, incluindo as principais moedas do mundo, para fins de negociação, investimento ou outras finalidades financeiras. Além dos preços de ações das principais empresas brasileiras.
Home-page: UNKNOWN
Author: Eduardo de Sousa e Carlos Henrique
Author-email: eduardosousa1718@gmail.com, ch123carlos@gmail.com
License: MIT License
Keywords: berry check
Platform: UNKNOWN
License-File: LICENSE
Requires-Dist: requests
Requires-Dist: bs4
Requires-Dist: typing
Requires-Dist: yfinance
